{
  "kind": "collectionType",
  "collectionName": "partners",
  "info": {
    "singularName": "partner",
    "pluralName": "partners",
    "displayName": "Partner",
    "description": "Partenaires de l'école"
  },
  "options": {
    "draftAndPublish": true
  },
  "pluginOptions": {},
  "attributes": {
    "nom": {
      "type": "string",
      "required": true
    },
    "logo": {
      "type": "media",
      "multiple": false,
      "required": false,
      "allowedTypes": [
        "images"
      ]
    },
    "description": {
      "type": "text"
    },
    "siteWeb": {
      "type": "string"
    },
    "secteur": {
      "type": "string"
    },
    "ordre": {
      "type": "integer",
      "default": 0
    },
    "featured": {
      "type": "boolean",
      "default": false
    }
  }
}